MANIFEST.in
setup.py
test.py
.lib/easy_install.py
.lib/about/Trove-classifiers.txt
.lib/about/__init__.py
.lib/about/about.py
.lib/about-5.2.dist-info/DESCRIPTION.rst
.lib/about-5.2.dist-info/INSTALLER
.lib/about-5.2.dist-info/METADATA
.lib/about-5.2.dist-info/RECORD
.lib/about-5.2.dist-info/WHEEL
.lib/about-5.2.dist-info/metadata.json
.lib/about-5.2.dist-info/pbr.json
.lib/about-5.2.dist-info/top_level.txt
.lib/pkg_resources/__init__.py
.lib/pkg_resources/py31compat.py
.lib/pkg_resources/_vendor/__init__.py
.lib/pkg_resources/_vendor/appdirs.py
.lib/pkg_resources/_vendor/pyparsing.py
.lib/pkg_resources/_vendor/six.py
.lib/pkg_resources/_vendor/packaging/__about__.py
.lib/pkg_resources/_vendor/packaging/__init__.py
.lib/pkg_resources/_vendor/packaging/_compat.py
.lib/pkg_resources/_vendor/packaging/_structures.py
.lib/pkg_resources/_vendor/packaging/markers.py
.lib/pkg_resources/_vendor/packaging/requirements.py
.lib/pkg_resources/_vendor/packaging/specifiers.py
.lib/pkg_resources/_vendor/packaging/utils.py
.lib/pkg_resources/_vendor/packaging/version.py
.lib/pkg_resources/extern/__init__.py
.lib/setuptools/__init__.py
.lib/setuptools/archive_util.py
.lib/setuptools/build_meta.py
.lib/setuptools/cli-32.exe
.lib/setuptools/cli-64.exe
.lib/setuptools/cli.exe
.lib/setuptools/config.py
.lib/setuptools/dep_util.py
.lib/setuptools/depends.py
.lib/setuptools/dist.py
.lib/setuptools/extension.py
.lib/setuptools/glibc.py
.lib/setuptools/glob.py
.lib/setuptools/gui-32.exe
.lib/setuptools/gui-64.exe
.lib/setuptools/gui.exe
.lib/setuptools/launch.py
.lib/setuptools/lib2to3_ex.py
.lib/setuptools/monkey.py
.lib/setuptools/msvc.py
.lib/setuptools/namespaces.py
.lib/setuptools/package_index.py
.lib/setuptools/pep425tags.py
.lib/setuptools/py27compat.py
.lib/setuptools/py31compat.py
.lib/setuptools/py33compat.py
.lib/setuptools/py36compat.py
.lib/setuptools/sandbox.py
.lib/setuptools/script (dev).tmpl
.lib/setuptools/script.tmpl
.lib/setuptools/site-patch.py
.lib/setuptools/ssl_support.py
.lib/setuptools/unicode_utils.py
.lib/setuptools/version.py
.lib/setuptools/wheel.py
.lib/setuptools/windows_support.py
.lib/setuptools-38.5.1.dist-info/DESCRIPTION.rst
.lib/setuptools-38.5.1.dist-info/INSTALLER
.lib/setuptools-38.5.1.dist-info/LICENSE.txt
.lib/setuptools-38.5.1.dist-info/METADATA
.lib/setuptools-38.5.1.dist-info/RECORD
.lib/setuptools-38.5.1.dist-info/WHEEL
.lib/setuptools-38.5.1.dist-info/dependency_links.txt
.lib/setuptools-38.5.1.dist-info/entry_points.txt
.lib/setuptools-38.5.1.dist-info/metadata.json
.lib/setuptools-38.5.1.dist-info/top_level.txt
.lib/setuptools-38.5.1.dist-info/zip-safe
.lib/setuptools/command/__init__.py
.lib/setuptools/command/alias.py
.lib/setuptools/command/bdist_egg.py
.lib/setuptools/command/bdist_rpm.py
audio.timit.egg-info/PKG-INFO
audio.timit.egg-info/SOURCES.txt
audio.timit.egg-info/dependency_links.txt
audio.timit.egg-info/requires.txt
audio.timit.egg-info/top_level.txt