Metadata-Version: 1.0
Name: audio.timit
Version: 0.1
Summary: Acoustic-Phonetic Index
Home-page: UNKNOWN
Author: Sébastien Boisgérault
Author-email: Sebastien.Boisgerault@mines-paristech.fr
License: MIT License
Platform: UNKNOWN
